calotron/__init__.py
calotron/version.py
calotron/callbacks/AttnMaskIgnition.py
calotron/callbacks/__init__.py
calotron/callbacks/schedulers/AdvBaseDamping.py
calotron/callbacks/schedulers/AdvExpDamping.py
calotron/callbacks/schedulers/AdvLinearDamping.py
calotron/callbacks/schedulers/LearnRateAttnDecay.py
calotron/callbacks/schedulers/LearnRateBaseScheduler.py
calotron/callbacks/schedulers/LearnRateCosineDecay.py
calotron/callbacks/schedulers/LearnRateExpDecay.py
calotron/callbacks/schedulers/LearnRateInvTimeDecay.py
calotron/callbacks/schedulers/LearnRatePiecewiseConstDecay.py
calotron/callbacks/schedulers/LearnRatePolynomialDecay.py
calotron/callbacks/schedulers/__init__.py
calotron/layers/Attention.py
calotron/layers/Decoder.py
calotron/layers/DeepSets.py
calotron/layers/Encoder.py
calotron/layers/MultiActivations.py
calotron/layers/MultilayerPerceptron.py
calotron/layers/SeqOrderEmbedding.py
calotron/layers/__init__.py
calotron/losses/BaseLoss.py
calotron/losses/BinaryCrossentropy.py
calotron/losses/ConservationLaw.py
calotron/losses/Huber.py
calotron/losses/JSDivergence.py
calotron/losses/KLDivergence.py
calotron/losses/MeanAbsoluteError.py
calotron/losses/MeanSquaredError.py
calotron/losses/WassersteinDistance.py
calotron/losses/__init__.py
calotron/metrics/Accuracy.py
calotron/metrics/BaseMetric.py
calotron/metrics/BinaryCrossentropy.py
calotron/metrics/JSDivergence.py
calotron/metrics/KLDivergence.py
calotron/metrics/MeanAbsoluteError.py
calotron/metrics/MeanSquaredError.py
calotron/metrics/RootMeanSquaredError.py
calotron/metrics/WassersteinDistance.py
calotron/metrics/__init__.py
calotron/models/Calogantron.py
calotron/models/Calotron.py
calotron/models/Generator.py
calotron/models/__init__.py
calotron/models/discriminators/BaseDiscriminator.py
calotron/models/discriminators/Discriminator.py
calotron/models/discriminators/GNNDiscriminator.py
calotron/models/discriminators/PairwiseDiscriminator.py
calotron/models/discriminators/__init__.py
calotron-0.0.12.dist-info/LICENSE
calotron-0.0.12.dist-info/METADATA
calotron-0.0.12.dist-info/WHEEL
calotron-0.0.12.dist-info/top_level.txt
calotron-0.0.12.dist-info/RECORD
