Metadata-Version: 2.1
Name: calotron
Version: 0.0.12
Summary: Transformer-based models to fast-simulate the LHCb ECAL detector
Author-email: Matteo Barbetti <matteo.barbetti@fi.infn.it>, Lucio Anderlini <lucio.anderlini@fi.infn.it>
License: GPLv3 License
Project-URL: repository, https://github.com/mbarbetti/calotron
Keywords: tensorflow,machine learning,deep learning,transformer,lhcb experiment,lamarr,ultra-fast simulation,calorimeter
Classifier: Development Status :: 3 - Alpha
Classifier: Intended Audience :: Science/Research
Classifier: License :: OSI Approved :: GNU General Public License v3 (GPLv3)
Classifier: Programming Language :: Python :: 3.7
Classifier: Programming Language :: Python :: 3.8
Classifier: Programming Language :: Python :: 3.9
Classifier: Programming Language :: Python :: 3.10
Classifier: Programming Language :: Python :: 3.11
Classifier: Topic :: Scientific/Engineering :: Physics
Classifier: Topic :: Scientific/Engineering :: Artificial Intelligence
Requires-Python: <=3.11,>=3.7
License-File: LICENSE
Requires-Dist: tensorflow (>=2.10)
Requires-Dist: pyyaml
Provides-Extra: lamarr
Requires-Dist: numpy ; extra == 'lamarr'
Requires-Dist: pandas ; extra == 'lamarr'
Requires-Dist: uproot ; extra == 'lamarr'
Requires-Dist: matplotlib ; extra == 'lamarr'
Requires-Dist: scikit-learn ; extra == 'lamarr'
Requires-Dist: html-reports (>=0.2) ; extra == 'lamarr'
Provides-Extra: style
Requires-Dist: black ; extra == 'style'
Requires-Dist: flake8 ; extra == 'style'
Requires-Dist: isort[colors] ; extra == 'style'
Provides-Extra: tests
Requires-Dist: pytest (>=6.0) ; extra == 'tests'
Requires-Dist: pytest-cov ; extra == 'tests'
